<?xml version="1.0" encoding="UTF-8"?>
<HaworthOrders><FileName>WIRETECH_FABRICATORS_INC_101756128</FileName><Order type="NB"><OrderType></OrderType><OrderNumber>4501592039.00010.0001</OrderNumber><VariantName>3025</VariantName><OrgCode>1400</OrgCode><OrgName></OrgName><StatusCode>REL</StatusCode><ChangeDate>09/19/2015 04:17:15</ChangeDate><BuyerID>024</BuyerID><PlannerID>490</PlannerID><DockDate>10/09/2015</DockDate><SupplierNumber>0000936088</SupplierNumber><SupplierName>Wiretech Fabricators Inc</SupplierName><PartInformation><Description>FRAME,CHAIR,VERY WS,NO_AR</Description><Description2>M,CHRM,USA,KR_V</Description2><ColorCode></ColorCode><ColorPattern></ColorPattern><ColorDescription></ColorDescription><EngineeringDrawingNumber>4538-9700</EngineeringDrawingNumber><RevisionLevel></RevisionLevel><Characteristics><ArmStyle>NO_ARM</ArmStyle><SeatMaterial>PLST</SeatMaterial><BackJacket>NO_BKJCK</BackJacket><FireCode>NO_COD Surface Treatment</FireCode><FrontSide>NO_TREAT</FrontSide><Seat1Color>TR_FJ</Seat1Color><Seat2Color>NO_COL</Seat2Color><Back1ColorInside>TR_FJ</Back1ColorInside><FrameColor>KR_V</FrameColor><TrimColor>NO_COL</TrimColor></Characteristics></PartInformation><ItemNumber>000000001151598</ItemNumber><LegacyPart>453897030000V0</LegacyPart><ItemCategory></ItemCategory><RequiredQty>80.000</RequiredQty><ReceivedQty>0.000</ReceivedQty><UOM>PER 1 EA</UOM><UnitPrice>20.4</UnitPrice><CurrencyType>USD</CurrencyType><PartWeight></PartWeight><CartonWeight></CartonWeight><CartonLength>0</CartonLength><CartonWidth>0</CartonWidth><CartonHeight>0</CartonHeight><DeliveryInformation><PlantCode>3025</PlantCode><PlantName>Haworth, Inc.</PlantName><PlantName2>Haworth Bruce Manufacturing</PlantName2><Address>225 South Thompson</Address><Address2></Address2><City>Bruce</City><State>MS</State><ZipCode>38915</ZipCode><Country>US</Country></DeliveryInformation><LeadTime></LeadTime><ShippingInstructions></ShippingInstructions><PurchText></PurchText><PurchText2></PurchText2><ItemConfiguration></ItemConfiguration><TransType>New</TransType><MaintenanceDateTime>09/19/2015 04:17:15</MaintenanceDateTime><ImportDateTime>09/19/2015 04:20:14</ImportDateTime></Order></HaworthOrders>